{
    "_comment": "日本語入力の場合２３文字までです",
    "opening": {
        "1": {
            "speaker": "Tuichan",
            "line": ["こんにちはこんにちはこんにちはこんにちはこんに", "僕の名前はTuichanです。", "君は誰だい"]
        },
        "2": {
            "speaker": "謎の子",
            "line": ["...", "...", "名前はまだない"]
        }
    },
    "nonta_talk1": {
        "1": {
            "speaker": "のん太",
            "line": ["おはよう", "やっと僕のことが見えるようになったかな", ""]
        },
        "2": {
            "speaker": "のん太",
            "line": ["やっぱり１６歳にならないと僕のことは見えるよう", "にはならないんだろうね", ""]
        },
        "3": {
            "speaker": "のん太",
            "line": ["何でもないよ", "それより君は”ガンデア”にそっくりだ", ""]
        },
        "4": {
            "speaker": "のん太",
            "line": ["”ガンデア”が分からないのかい", "それでも息子なのかな", ""]
        },
        "5": {
            "speaker": "のん太",
            "line": ["ガンデアは君のお父さんの名だよ", "君のお父さんはとても勇敢な人だった", ""]
        },
        "6": {
            "speaker": "のん太",
            "line": ["そうだ、お父さんと同じような旅をしてみたいと思", "わないかい", ""]
        },
        "7": {
            "speaker": "のん太",
            "line": ["よし、それでこそガンデアの息子だ", "", ""]
        },
        "8": {
            "speaker": "のん太",
            "line": ["", "", ""]
        }
    }
}